learncube/__init__.py
learncube/core.py
learncube/virtual_classroom/__init__.py
learncube/virtual_classroom/classroom.py
learncube/virtual_classroom/logs.py
learncube/virtual_classroom/participants.py
learncube-0.1.0.dist-info/LICENSE
learncube-0.1.0.dist-info/METADATA
learncube-0.1.0.dist-info/WHEEL
learncube-0.1.0.dist-info/top_level.txt
learncube-0.1.0.dist-info/RECORD
