Metadata-Version: 2.1
Name: learncube
Version: 0.1.0
Summary: A Python wrapper for the Learncube API
Home-page: https://github.com/Bueffelheld/learncube-python
Author: Fabian Riewe
Author-email: f.riewe@bueffelehld.de
License: UNKNOWN
Platform: UNKNOWN
Classifier: Programming Language :: Python :: 3
Classifier: License :: OSI Approved :: MIT License
Classifier: Operating System :: OS Independent
Requires-Python: >=3.6
